reportfy/__init__.py
reportfy/jinja_helper.py
reportfy/charts/__init__.py
reportfy/charts/axes.py
reportfy/charts/ichart.py
reportfy/charts/series.py
reportfy-0.0.1.dist-info/LICENSE
reportfy-0.0.1.dist-info/METADATA
reportfy-0.0.1.dist-info/WHEEL
reportfy-0.0.1.dist-info/top_level.txt
reportfy-0.0.1.dist-info/RECORD
