Metadata-Version: 2.1
Name: reportfy
Version: 0.0.1
Summary: Generate html single page report dashboards
Home-page: https://github.com/rjanuzi/reportfy
Author: Rafael B. Januzi
Author-email: rjanuzi@gmail.com
License: UNKNOWN
Project-URL: Bug Tracker, https://github.com/rjanuzi/reportfy/issues
Platform: UNKNOWN
Classifier: Programming Language :: Python :: 3
Classifier: License :: OSI Approved :: MIT License
Classifier: Operating System :: OS Independent
Requires-Python: >=3.8
License-File: LICENSE
